Workbook

Sheet README
B2: Daftar Advisory revenue model
B3: Editable 12-month launch model for MENA remote and Jordan finance advisory
B5: Purpose | C5: Model revenue potential across three launch angles: Startup CFO / Investor Readiness, SME Finance Advisory, and Fractional Finance Desk.
B6: How to use | C6: Edit yellow input cells on the Assumptions sheet. Revenue Model, Sensitivity, and charts update from formulas.
B7: Default recommendation | C7: Prioritize Investor Readiness first, run SME Finance Advisory in parallel, and use Fractional Finance Desk as an upsell after project trust is established.
B8: Currency | C8: USD for fees; founder costs JOD-denominated. USD/JOD and a 10% FX shock are now modelled on the Assumptions sheet (C50:C51).
B9: Important | C9: Decision-grade estimates, not guarantees. Project fees split 50% at signing / 50% at delivery. Cash balance includes starting cash and Month-0 setup. See Capacity sheet for solo-founder feasibility. Replace assumptions with real pipeline data after the first 10 discovery calls.
B11: Revision log
C12: Cash timing: project fees now 50% win / 50% delivery (was 100% at win).
C13: Added FX line + 10% shock; JOD cost context.
C14: Added starting cash + Month-0 setup -> true cash balance.
C15: New Capacity sheet: founder hours vs pipeline demand.
C16: Sensitivity retitled (Investor Ready project revenue only); denominator fixed to 0.35.
C17: Retainer cascade cleaned (removed dead IF code).
C18: Cost lines expanded (taxes, accounting, banking/FX, contingency).
C19: Pipeline Leads marked INTERNAL.

Sheet Assumptions
B2: Assumptions
B3: Yellow cells are inputs. All revenue calculations are formula-driven.
B5: Scenario | C5: Base
B6: Launch focus | C6: Investor Readiness first; SME advisory second; fractional desk as upsell
B9: Offer | C9: Angle | D9: Avg Fixed Fee ($) | E9: Low Fee ($) | F9: High Fee ($) | G9: Delivery Weeks | H9: Retainer Upsell % | I9: Monthly Retainer ($) | P9: Base Avg Fee
B10: Investor Ready | C10: Startup CFO / Investor Readiness | D10: =P10*$C$43 -> 12500 | E10: 9000 | F10: 16000 | G10: 4 | H10: 0.25 | I10: 3000 | P10: 12500
B11: Pre-Audit Cleanup | C11: SME Finance Advisory | D11: =P11*$C$43 -> 7500 | E11: 5000 | F11: 10000 | G11: 3 | H11: 0.15 | I11: 2500 | P11: 7500
B12: Monthly Finance Desk | C12: Fractional Finance Desk | D12: =P12*$C$43 -> 0 | E12: 0 | F12: 0 | G12: 12 | H12: 1 | I12: 3500 | P12: 0
B16: Metric | C16: Month 1 | D16: Month 2 | E16: Month 3 | F16: Month 4 | G16: Month 5 | H16: Month 6 | I16: Month 7 | J16: Month 8 | K16: Month 9 | L16: Month 10 | M16: Month 11 | N16: Month 12
B17: Outreach sent | C17: 15 | D17: 18 | E17: 20 | F17: 22 | G17: 24 | H17: 26 | I17: 28 | J17: 30 | K17: 32 | L17: 34 | M17: 36 | N17: 38
B18: Discovery call rate | C18: 0.2 | D18: 0.2 | E18: 0.2 | F18: 0.2 | G18: 0.2 | H18: 0.2 | I18: 0.2 | J18: 0.2 | K18: 0.2 | L18: 0.2 | M18: 0.2 | N18: 0.2
B19: Proposal rate from calls | C19: 0.45 | D19: 0.45 | E19: 0.45 | F19: 0.45 | G19: 0.45 | H19: 0.45 | I19: 0.45 | J19: 0.45 | K19: 0.45 | L19: 0.45 | M19: 0.45 | N19: 0.45
B20: Win rate from proposals | C20: =C46*$C$42 -> 0.3 | D20: =D46*$C$42 -> 0.3 | E20: =E46*$C$42 -> 0.32 | F20: =F46*$C$42 -> 0.32 | G20: =G46*$C$42 -> 0.34 | H20: =H46*$C$42 -> 0.34 | I20: =I46*$C$42 -> 0.36 | J20: =J46*$C$42 -> 0.36 | ... N20: =N46*$C$42 -> 0.4
B21: Investor Ready mix | C21: 0.55 | D21: 0.55 | E21: 0.55 | F21: 0.5 | G21: 0.5 | H21: 0.48 | I21: 0.48 | J21: 0.45 | K21: 0.45 | L21: 0.43 | M21: 0.43 | N21: 0.4
B22: Pre-Audit Cleanup mix | C22: 0.35 | D22: 0.35 | E22: 0.35 | F22: 0.38 | G22: 0.38 | H22: 0.4 | I22: 0.4 | J22: 0.42 | K22: 0.42 | L22: 0.42 | M22: 0.42 | N22: 0.42
B23: Monthly Finance Desk direct mix | C23: 0.1 | D23: 0.1 | E23: 0.1 | F23: 0.12 | G23: 0.12 | H23: 0.12 | I23: 0.12 | J23: 0.13 | K23: 0.13 | L23: 0.15 | M23: 0.15 | N23: 0.18
B24: Lead source capacity cap | C24: 3 | D24: 3 | E24: 4 | F24: 4 | G24: 5 | H24: 5 | I24: 6 | J24: 6 | K24: 7 | L24: 7 | M24: 8 | N24: 8
B28: Cost line | C28: Month 1 | D28: Month 2 | E28: Month 3 | F28: Month 4 | G28: Month 5 | H28: Month 6 | I28: Month 7 | J28: Month 8 | K28: Month 9 | L28: Month 10 | M28: Month 11 | N28: Month 12
B29: Founder draw / living buffer | C29: 2500 | D29: 2500 | E29: 2500 | F29: 2500 | G29: 2500 | H29: 2500 | I29: 2500 | J29: 2500 | K29: 2500 | L29: 2500 | M29: 2500 | N29: 2500
B30: Tools, software, website | C30: 350 | D30: 350 | E30: 300 | F30: 300 | G30: 300 | H30: 300 | I30: 300 | J30: 300 | K30: 300 | L30: 300 | M30: 300 | N30: 300
B31: Marketing, travel, coffee, events | C31: 700 | D31: 800 | E31: 900 | F31: 900 | G31: 1000 | H31: 1000 | I31: 1100 | J31: 1100 | K31: 1200 | L31: 1200 | M31: 1300 | N31: 1300
B32: Professional insurance / legal | C32: 500 | D32: 150 | E32: 150 | F32: 150 | G32: 150 | H32: 150 | I32: 150 | J32: 150 | K32: 150 | L32: 150 | M32: 150 | N32: 150
B33: Taxes / withholding provision | C33: 400 | D33: 400 | E33: 400 | F33: 400 | G33: 400 | H33: 400 | I33: 400 | J33: 400 | K33: 400 | L33: 400 | M33: 400 | N33: 400
B34: Accounting for own books | C34: 120 | D34: 120 | E34: 120 | F34: 120 | G34: 120 | H34: 120 | I34: 120 | J34: 120 | K34: 120 | L34: 120 | M34: 120 | N34: 120
B35: Banking / FX fees | C35: 80 | D35: 80 | E35: 80 | F35: 80 | G35: 80 | H35: 80 | I35: 80 | J35: 80 | K35: 80 | L35: 80 | M35: 80 | N35: 80
B36: Contingency buffer | C36: 250 | D36: 250 | E36: 250 | F36: 250 | G36: 250 | H36: 250 | I36: 250 | J36: 250 | K36: 250 | L36: 250 | M36: 250 | N36: 250
B37: Scenario | C37: Win-rate x | D37: Fee x
B38: Base | C38: 1 | D38: 1
B39: Conservative | C39: 0.7 | D39: 0.85
B40: Aggressive | C40: 1.3 | D40: 1.15
B42: Active win-rate multiplier | C42: =VLOOKUP($C$5,$B$38:$D$40,2,FALSE()) -> 1
B43: Active fee multiplier | C43: =VLOOKUP($C$5,$B$38:$D$40,3,FALSE()) -> 1
B46: Base win rate (pre-scenario) | C46: 0.3 | D46: 0.3 | E46: 0.32 | F46: 0.32 | G46: 0.34 | H46: 0.34 | I46: 0.36 | J46: 0.36 | K46: 0.38 | L46: 0.38 | M46: 0.4 | N46: 0.4
B49: FX & cash setup
B50: USD per 1 JOD (quote fees in USD, pay costs in JOD) | C50: 1.41
B51: FX shock applied to USD revenue (1.0 = none) | C51: 1
B52: Starting cash (bank balance, Month 0) | C52: 15000
B53: Month-0 setup costs (registration, branding, website, licenses) | C53: 6000

Sheet Revenue Model
B2: 12-month revenue model
B3: Formula-driven model using Assumptions sheet inputs
B5: Line item | C5: Month 1 | D5: Month 2 | E5: Month 3 | F5: Month 4 | G5: Month 5 | H5: Month 6 | I5: Month 7 | J5: Month 8 | K5: Month 9 | L5: Month 10 | M5: Month 11 | N5: Month 12 | O5: Year 1 Total
B6: Outreach sent | C6: =Assumptions!C17 -> 15 | D6: =Assumptions!D17 -> 18 | E6: =Assumptions!E17 -> 20 | F6: =Assumptions!F17 -> 22 | G6: =Assumptions!G17 -> 24 | H6: =Assumptions!H17 -> 26 | I6: =Assumptions!I17 -> 28 | J6: =Assumptions!J17 -> 30 | ... N6: =Assumptions!N17 -> 38 | O6: =SUM(C6:N6) -> 323
B7: Discovery calls | C7: =MIN(C6*Assumptions!C18,Assumptions!C24) -> 3 | D7: =MIN(D6*Assumptions!D18,Assumptions!D24) -> 3 | E7: =MIN(E6*Assumptions!E18,Assumptions!E24) -> 4 | F7: =MIN(F6*Assumptions!F18,Assumptions!F24) -> 4 | G7: =MIN(G6*Assumptions!G18,Assumptions!G24) -> 4.8 | H7: =MIN(H6*Assumptions!H18,Assumptions!H24) -> 5 | I7: =MIN(I6*Assumptions!I18,Assumptions!I24) -> 5.6 | J7: =MIN(J6*Assumptions!J18,Assumptions!J24) -> 6 | ... N7: =MIN(N6*Assumptions!N18,Assumptions!N24) -> 7.6 | O7: =SUM(C7:N7) -> 63.4
B8: Proposals sent | C8: =C7*Assumptions!C19 -> 1.35 | D8: =D7*Assumptions!D19 -> 1.35 | E8: =E7*Assumptions!E19 -> 1.8 | F8: =F7*Assumptions!F19 -> 1.8 | G8: =G7*Assumptions!G19 -> 2.16 | H8: =H7*Assumptions!H19 -> 2.25 | I8: =I7*Assumptions!I19 -> 2.52 | J8: =J7*Assumptions!J19 -> 2.7 | ... N8: =N7*Assumptions!N19 -> 3.42 | O8: =SUM(C8:N8) -> 28.53
B9: Won engagements | C9: =C8*Assumptions!C20 -> 0.405 | D9: =D8*Assumptions!D20 -> 0.405 | E9: =E8*Assumptions!E20 -> 0.576 | F9: =F8*Assumptions!F20 -> 0.576 | G9: =G8*Assumptions!G20 -> 0.7344 | H9: =H8*Assumptions!H20 -> 0.765 | I9: =I8*Assumptions!I20 -> 0.9072 | J9: =J8*Assumptions!J20 -> 0.972 | ... N9: =N8*Assumptions!N20 -> 1.368 | O9: =SUM(C9:N9) -> 10.2618
B10: Investor Ready projects won | C10: =C9*Assumptions!C21 -> 0.22275 | D10: =D9*Assumptions!D21 -> 0.22275 | E10: =E9*Assumptions!E21 -> 0.3168 | F10: =F9*Assumptions!F21 -> 0.288 | G10: =G9*Assumptions!G21 -> 0.3672 | H10: =H9*Assumptions!H21 -> 0.3672 | I10: =I9*Assumptions!I21 -> 0.435456 | J10: =J9*Assumptions!J21 -> 0.4374 | ... N10: =N9*Assumptions!N21 -> 0.5472 | O10: =SUM(C10:N10) -> 4.75452
B11: Pre-Audit Cleanup projects won | C11: =C9*Assumptions!C22 -> 0.14175 | D11: =D9*Assumptions!D22 -> 0.14175 | E11: =E9*Assumptions!E22 -> 0.2016 | F11: =F9*Assumptions!F22 -> 0.21888 | G11: =G9*Assumptions!G22 -> 0.279072 | H11: =H9*Assumptions!H22 -> 0.306 | I11: =I9*Assumptions!I22 -> 0.36288 | J11: =J9*Assumptions!J22 -> 0.40824 | ... N11: =N9*Assumptions!N22 -> 0.57456 | O11: =SUM(C11:N11) -> 4.127076
B12: Monthly Finance Desk direct wins | C12: =C9*Assumptions!C23 -> 0.0405 | D12: =D9*Assumptions!D23 -> 0.0405 | E12: =E9*Assumptions!E23 -> 0.0576 | F12: =F9*Assumptions!F23 -> 0.06912 | G12: =G9*Assumptions!G23 -> 0.088128 | H12: =H9*Assumptions!H23 -> 0.0918 | I12: =I9*Assumptions!I23 -> 0.108864 | J12: =J9*Assumptions!J23 -> 0.12636 | ... N12: =N9*Assumptions!N23 -> 0.24624 | O12: =SUM(C12:N12) -> 1.380204
B13: Investor Ready project revenue (booked) | C13: =C10*Assumptions!$D$10*Assumptions!$C$51 -> 2784.375 | D13: =D10*Assumptions!$D$10*Assumptions!$C$51 -> 2784.375 | E13: =E10*Assumptions!$D$10*Assumptions!$C$51 -> 3960 | F13: =F10*Assumptions!$D$10*Assumptions!$C$51 -> 3600 | G13: =G10*Assumptions!$D$10*Assumptions!$C$51 -> 4590 | H13: =H10*Assumptions!$D$10*Assumptions!$C$51 -> 4590 | I13: =I10*Assumptions!$D$10*Assumptions!$C$51 -> 5443.2 | J13: =J10*Assumptions!$D$10*Assumptions!$C$51 -> 5467.5 | ... N13: =N10*Assumptions!$D$10*Assumptions!$C$51 -> 6840 | O13: =SUM(C13:N13) -> 59431.5
B14: Pre-Audit project revenue (booked) | C14: =C11*Assumptions!$D$11*Assumptions!$C$51 -> 1063.125 | D14: =D11*Assumptions!$D$11*Assumptions!$C$51 -> 1063.125 | E14: =E11*Assumptions!$D$11*Assumptions!$C$51 -> 1512 | F14: =F11*Assumptions!$D$11*Assumptions!$C$51 -> 1641.6 | G14: =G11*Assumptions!$D$11*Assumptions!$C$51 -> 2093.04 | H14: =H11*Assumptions!$D$11*Assumptions!$C$51 -> 2295 | I14: =I11*Assumptions!$D$11*Assumptions!$C$51 -> 2721.6 | J14: =J11*Assumptions!$D$11*Assumptions!$C$51 -> 3061.8 | ... N14: =N11*Assumptions!$D$11*Assumptions!$C$51 -> 4309.2 | O14: =SUM(C14:N14) -> 30953.07
B15: IR project cash collected (50% win / 50% delivery) | C15: =0.5*C13 -> 1392.1875 | D15: =0.5*D13+0.5*C13 -> 2784.375 | E15: =0.5*E13+0.5*D13 -> 3372.1875 | F15: =0.5*F13+0.5*E13 -> 3780 | G15: =0.5*G13+0.5*F13 -> 4095 | H15: =0.5*H13+0.5*G13 -> 4590 | I15: =0.5*I13+0.5*H13 -> 5016.6 | J15: =0.5*J13+0.5*I13 -> 5455.35 | K15: =0.5*K13+0.5*J13 -> 5811.75 | ... N15: =0.5*N13+0.5*M13 -> 6903 | O15: =SUM(C15:N15) -> 56011.5
B16: Pre-Audit project cash collected | C16: =0.5*C14 -> 531.5625 | D16: =0.5*D14+0.5*C14 -> 1063.125 | E16: =0.5*E14+0.5*D14 -> 1287.5625 | F16: =0.5*F14+0.5*E14 -> 1576.8 | G16: =0.5*G14+0.5*F14 -> 1867.32 | H16: =0.5*H14+0.5*G14 -> 2194.02 | I16: =0.5*I14+0.5*H14 -> 2508.3 | J16: =0.5*J14+0.5*I14 -> 2891.7 | K16: =0.5*K14+0.5*J14 -> 3254.58 | ... N16: =0.5*N14+0.5*M14 -> 4195.8 | O16: =SUM(C16:N16) -> 28798.47
B17: New monthly retainer revenue | C17: =(C10*Assumptions!$H$10*Assumptions!$I$10)+(C11*Assumptions!$H$11*Assumptions!$I$11)+(C12*Assumptions!$I$12) -> 361.96875 | D17: =(D10*Assumptions!$H$10*Assumptions!$I$10)+(D11*Assumptions!$H$11*Assumptions!$I$11)+(D12*Assumptions!$I$12) -> 361.96875 | E17: =(E10*Assumptions!$H$10*Assumptions!$I$10)+(E11*Assumptions!$H$11*Assumptions!$I$11)+(E12*Assumptions!$I$12) -> 514.8 | F17: =(F10*Assumptions!$H$10*Assumptions!$I$10)+(F11*Assumptions!$H$11*Assumptions!$I$11)+(F12*Assumptions!$I$12) -> 540 | G17: =(G10*Assumptions!$H$10*Assumptions!$I$10)+(G11*Assumptions!$H$11*Assumptions!$I$11)+(G12*Assumptions!$I$12) -> 688.5 | H17: =(H10*Assumptions!$H$10*Assumptions!$I$10)+(H11*Assumptions!$H$11*Assumptions!$I$11)+(H12*Assumptions!$I$12) -> 711.45 | I17: =(I10*Assumptions!$H$10*Assumptions!$I$10)+(I11*Assumptions!$H$11*Assumptions!$I$11)+(I12*Assumptions!$I$12) -> 843.696 | J17: =(J10*Assumptions!$H$10*Assumptions!$I$10)+(J11*Assumptions!$H$11*Assumptions!$I$11)+(J12*Assumptions!$I$12) -> 923.4 | ... N17: =(N10*Assumptions!$H$10*Assumptions!$I$10)+(N11*Assumptions!$H$11*Assumptions!$I$11)+(N12*Assumptions!$I$12) -> 1487.7 | O17: =SUM(C17:N17) -> 9944.2575
B18: Retainer revenue from prior months | C18: =0 -> 0 | D18: =C17+C18 -> 361.96875 | E18: =D17+D18 -> 723.9375 | F18: =E17+E18 -> 1238.7375 | G18: =F17+F18 -> 1778.7375 | H18: =G17+G18 -> 2467.2375 | I18: =H17+H18 -> 3178.6875 | J18: =I17+I18 -> 4022.3835 | K18: =J17+J18 -> 4945.7835 | ... N18: =M17+M18 -> 8456.5575 | O18: =SUM(C18:N18) -> 40313.572
B19: Project cash collected (subtotal) | C19: =C15+C16 -> 1923.75 | D19: =D15+D16 -> 3847.5 | E19: =E15+E16 -> 4659.75 | F19: =F15+F16 -> 5356.8 | G19: =G15+G16 -> 5962.32 | H19: =H15+H16 -> 6784.02 | I19: =I15+I16 -> 7524.9 | J19: =J15+J16 -> 8347.05 | ... N19: =N15+N16 -> 11098.8 | O19: =SUM(C19:N19) -> 84809.97
B20: Recurring retainer revenue (subtotal) | C20: =C17+C18 -> 361.96875 | D20: =D17+D18 -> 723.9375 | E20: =E17+E18 -> 1238.7375 | F20: =F17+F18 -> 1778.7375 | G20: =G17+G18 -> 2467.2375 | H20: =H17+H18 -> 3178.6875 | I20: =I17+I18 -> 4022.3835 | J20: =J17+J18 -> 4945.7835 | ... N20: =N17+N18 -> 9944.2575 | O20: =SUM(C20:N20) -> 50257.829
B21: Total cash collected | C21: =C19+C20 -> 2285.7188 | D21: =D19+D20 -> 4571.4375 | E21: =E19+E20 -> 5898.4875 | F21: =F19+F20 -> 7135.5375 | G21: =G19+G20 -> 8429.5575 | H21: =H19+H20 -> 9962.7075 | I21: =I19+I20 -> 11547.283 | J21: =J19+J20 -> 13292.834 | ... N21: =N19+N20 -> 21043.057 | O21: =SUM(C21:N21) -> 135067.8
B22: Memo: total booked revenue (accrual) | C22: =C13+C14+C17+C18 -> 4209.4688 | D22: =D13+D14+D17+D18 -> 4571.4375 | E22: =E13+E14+E17+E18 -> 6710.7375 | F22: =F13+F14+F17+F18 -> 7020.3375 | G22: =G13+G14+G17+G18 -> 9150.2775 | H22: =H13+H14+H17+H18 -> 10063.688 | I22: =I13+I14+I17+I18 -> 12187.183 | J22: =J13+J14+J17+J18 -> 13475.084 | ... N22: =N13+N14+N17+N18 -> 21093.458 | O22: =SUM(C22:N22) -> 140642.4
B23: Operating costs | C23: =SUM(Assumptions!C29:C36) -> 4900 | D23: =SUM(Assumptions!D29:D36) -> 4650 | E23: =SUM(Assumptions!E29:E36) -> 4700 | F23: =SUM(Assumptions!F29:F36) -> 4700 | G23: =SUM(Assumptions!G29:G36) -> 4800 | H23: =SUM(Assumptions!H29:H36) -> 4800 | I23: =SUM(Assumptions!I29:I36) -> 4900 | J23: =SUM(Assumptions!J29:J36) -> 4900 | ... N23: =SUM(Assumptions!N29:N36) -> 5100 | O23: =SUM(C23:N23) -> 58550
B24: Net cash before tax | C24: =C21-C23-Assumptions!$C$53 -> -8614.2812 | D24: =D21-D23 -> -78.5625 | E24: =E21-E23 -> 1198.4875 | F24: =F21-F23 -> 2435.5375 | G24: =G21-G23 -> 3629.5575 | H24: =H21-H23 -> 5162.7075 | I24: =I21-I23 -> 6647.2835 | J24: =J21-J23 -> 8392.8335 | K24: =K21-K23 -> 10051.793 | ... N24: =N21-N23 -> 15943.058 | O24: =SUM(C24:N24) -> 70517.799
B25: Cash balance (incl. starting cash) | C25: =Assumptions!$C$52+C24 -> 6385.7188 | D25: =C25+D24 -> 6307.1562 | E25: =D25+E24 -> 7505.6438 | F25: =E25+F24 -> 9941.1812 | G25: =F25+G24 -> 13570.739 | H25: =G25+H24 -> 18733.446 | I25: =H25+I24 -> 25380.73 | J25: =I25+J24 -> 33773.563 | K25: =J25+K24 -> 43825.357 | ... N25: =M25+N24 -> 85517.799 | O25: =N25 -> 85517.799

Sheet Sensitivity
B2: Sensitivity — Investor Ready project revenue only
B3: Year-1 INVESTOR READY PROJECT revenue (not total model revenue) by IR win rate and IR fee
B5: Investor Ready average fee sensitivity
B7: IR win rate / IR fee | C7: 9000 | D7: 11000 | E7: 12500 | F7: 14000 | G7: 16000
B8: 0.2 | C8: ='Revenue Model'!$O$13/Assumptions!$D$10/0.35*0.2*9000 -> 24451.817 | D8: ='Revenue Model'!$O$13/Assumptions!$D$10/0.35*0.2*11000 -> 29885.554 | E8: ='Revenue Model'!$O$13/Assumptions!$D$10/0.35*0.2*12500 -> 33960.857 | F8: ='Revenue Model'!$O$13/Assumptions!$D$10/0.35*0.2*14000 -> 38036.16 | G8: ='Revenue Model'!$O$13/Assumptions!$D$10/0.35*0.2*16000 -> 43469.897
B9: 0.25 | C9: ='Revenue Model'!$O$13/Assumptions!$D$10/0.35*0.25*9000 -> 30564.771 | D9: ='Revenue Model'!$O$13/Assumptions!$D$10/0.35*0.25*11000 -> 37356.943 | E9: ='Revenue Model'!$O$13/Assumptions!$D$10/0.35*0.25*12500 -> 42451.071 | F9: ='Revenue Model'!$O$13/Assumptions!$D$10/0.35*0.25*14000 -> 47545.2 | G9: ='Revenue Model'!$O$13/Assumptions!$D$10/0.35*0.25*16000 -> 54337.371
B10: 0.3 | C10: ='Revenue Model'!$O$13/Assumptions!$D$10/0.35*0.3*9000 -> 36677.726 | D10: ='Revenue Model'!$O$13/Assumptions!$D$10/0.35*0.3*11000 -> 44828.331 | E10: ='Revenue Model'!$O$13/Assumptions!$D$10/0.35*0.3*12500 -> 50941.286 | F10: ='Revenue Model'!$O$13/Assumptions!$D$10/0.35*0.3*14000 -> 57054.24 | G10: ='Revenue Model'!$O$13/Assumptions!$D$10/0.35*0.3*16000 -> 65204.846
B11: 0.35 | C11: ='Revenue Model'!$O$13/Assumptions!$D$10/0.35*0.35*9000 -> 42790.68 | D11: ='Revenue Model'!$O$13/Assumptions!$D$10/0.35*0.35*11000 -> 52299.72 | E11: ='Revenue Model'!$O$13/Assumptions!$D$10/0.35*0.35*12500 -> 59431.5 | F11: ='Revenue Model'!$O$13/Assumptions!$D$10/0.35*0.35*14000 -> 66563.28 | G11: ='Revenue Model'!$O$13/Assumptions!$D$10/0.35*0.35*16000 -> 76072.32
B12: 0.4 | C12: ='Revenue Model'!$O$13/Assumptions!$D$10/0.35*0.4*9000 -> 48903.634 | D12: ='Revenue Model'!$O$13/Assumptions!$D$10/0.35*0.4*11000 -> 59771.109 | E12: ='Revenue Model'!$O$13/Assumptions!$D$10/0.35*0.4*12500 -> 67921.714 | F12: ='Revenue Model'!$O$13/Assumptions!$D$10/0.35*0.4*14000 -> 76072.32 | G12: ='Revenue Model'!$O$13/Assumptions!$D$10/0.35*0.4*16000 -> 86939.794
B15: Decision readout
B16: Base Year 1 booked revenue | C16: ='Revenue Model'!O22 -> 140642.4
B17: Base Year 1 net cash before tax | C17: ='Revenue Model'!O24 -> 70517.799
B18: Year-end cash balance (incl. starting cash) | C18: ='Revenue Model'!O25 -> 85517.799
B19: First wedge | C19: Startup CFO / Investor Readiness
B20: Second wedge | C20: SME Finance Advisory
B21: Retainer path | C21: Convert project clients into Monthly Finance Desk after trust is established

Sheet Capacity
B2: Solo-founder delivery capacity check
B3: Tests whether one founder can deliver the modelled pipeline. Yellow cells are inputs.
B5: Productive hours per week | C5: 35
B6: Working weeks per year | C6: 48
B7: Hours per Investor Ready project | C7: 55
B8: Hours per Pre-Audit project | C8: 35
B9: Hours per Finance Desk retainer / month | C9: 10
B10: Hours per discovery call (incl prep) | C10: 1.5
B11: Hours per proposal | C11: 3
B12: Admin/ops hours per week | C12: 5
B14: Annual capacity (hours) | C14: =C5*C6 -> 1680
B15: Less admin/ops (hours/yr) | C15: =C12*C6 -> 240
B16: Net deliverable hours / year | C16: =C14-C15 -> 1440
B18: Annual demand (hours)
B19: Investor Ready delivery | C19: ='Revenue Model'!O10*C7 -> 261.4986
B20: Pre-Audit delivery | C20: ='Revenue Model'!O11*C8 -> 144.44766
B21: Finance Desk retainer delivery (retainer-months) | C21: =(SUM('Revenue Model'!C12:N12)+SUM('Revenue Model'!C10:N10)*Assumptions!H10+SUM('Revenue Model'!C11:N11)*Assumptions!H11)*6*C9 -> 191.27372
B22: Discovery calls | C22: ='Revenue Model'!O7*C10 -> 95.1
B23: Proposals | C23: ='Revenue Model'!O8*C11 -> 85.59
B24: Total demand hours / year | C24: =SUM(C19:C23) -> 777.90998
B26: Utilization (demand / net capacity) | C26: =C24/C16 -> 0.54021527
B27: Capacity verdict | C27: =IF(C26>1,"OVER CAPACITY — needs help or fewer wins",IF(C26>0.9,"TIGHT — >90% utilized",IF(C26>0.7,"OK — manageable","LOW — room to grow"))) -> LOW — room to grow

Sheet Pipeline Leads
B1: INTERNAL — DO NOT SHARE EXTERNALLY (commercial strategy: named targets + outreach hooks)
B3: First 5 lead targets
B4: Use as a live pipeline tracker for the first month
B6: Lead | C6: Country | D6: Angle | E6: Trigger signal | F6: Likely buyer | G6: Outreach hook | H6: Status | I6: Next action | J6: Source
B7: Abwaab | C7: Jordan / Egypt | D7: Startup CFO / Investor Readiness | E7: Apex Education acquisition; multi-entity consolidation and IFRS 3 accounting | F7: CFO / Finance Director | G7: Reference Apex acquisition; offer a 30-minute walk-through of purchase accounting and deferred revenue issues | H7: Not started | I7: Find warm intro or finance lead; send tailored LinkedIn message | J7: Wamda / TechCrunch
B8: Tamatem Games | C8: Jordan / Turkey | D8: Startup CFO / M&A accounting | E8: Playable Factory acquisition; IAS 21 and IFRS 3 complexity | F8: CEO / CFO / Finance Director | G8: Reference Turkey acquisition and audit surprises around functional currency and business combination treatment | H8: Not started | I8: Identify CFO/finance owner; send trigger-based note | J8: Wamda / PocketGamer
B9: Liwwa | C9: Jordan / Egypt | D9: Investor Readiness / Fractional Desk | E9: DFC loan, DFI covenants, Pre-Series B progression, Egypt operations | F9: CEO / CFO / Finance Director | G9: Reference DFI reporting covenants and IFRS 9 ECL across Jordan/Egypt | H9: Not started | I9: Seek DFI ecosystem intro; prepare IFRS 9/reporting hook | J9: Liwwa / IBS Intelligence / MAGNiTT
B10: WashyWash | C10: Jordan | D10: SME Finance Advisory / Investor Readiness | E10: Founder-led service SME featured as scalable Jordan startup | F10: Founder / CEO | G10: Reference Atlantic Council feature; connect finance cleanup to bank facility or next raise | H10: Not started | I10: Send founder-led SME note; offer quick finance-readiness diagnostic | J10: Atlantic Council / TechRound
B11: Manara Ventures portfolio | C11: Jordan | D11: Fund channel / Investor Readiness | E11: $70.5M fund launched; 20+ portfolio companies expected | F11: Partner / Investment Manager | G11: Offer fixed-scope readiness support for portfolio companies that cannot justify a full-time CFO yet | H11: Not started | I11: Ask for portfolio support/service-provider intro call | J11: Wamda / Manara Ventures
